{
    "app_version": "0.3.10",
    "method": 6,
    "class_id": 10,
    "class_name": "Ranger",
    "attr": {
        "st": {
            "score": 15,
            "atk_mod": 1,
            "dmg_adj": 1,
            "test": 3,
            "feat": 24
        },
        "dx": {
            "score": 14,
            "atk_mod": 0,
            "def_adj": 1,
            "test": 3,
            "feat": 8
        },
        "cn": {
            "score": 12,
            "hp_adj": 0,
            "poison_adj": 0,
            "trauma_surv": 75,
            "test": 2,
            "feat": 4
        },
        "in": {
            "score": 14,
            "lang": 1,
            "bonus_spells": 1,
            "learn_spell": 65
        },
        "ws": {
            "score": 10,
            "will_adj": 0,
            "bonus_spells": 0,
            "learn_spell": 50
        },
        "ch": {
            "score": 10,
            "react_adj": 0,
            "max_henchmen": 4,
            "turn_adj": 0
        }
    },
    "xp": 576000,
    "level": 11,
    "xp_to_next": 720000,
    "xp_bonus": false,
    "alignment": {
        "align_id": 2,
        "short_name": "CG",
        "long_name": "Chaotic Good"
    },
    "deity": {
        "deity_id": 21,
        "deity_name": "Ymir",
        "primary_alignment": "Chaotic"
    },
    "race_id": 24,
    "race": "Yakut",
    "gender": "Non-Binary",
    "secondary_skill": "fisherman/whaler",
    "hd": "9d10+6",
    "hp": 59,
    "fa": 11,
    "ca": 5,
    "ta": 0,
    "sv": 11,
    "sv_bonus": {
        "death": 2,
        "transformation": 2,
        "device": 0,
        "avoidance": 0,
        "sorcery": 0
    },
    "combat_matrix": {
        "-9": 18,
        "-8": 17,
        "-7": 16,
        "-6": 15,
        "-5": 14,
        "-4": 13,
        "-3": 12,
        "-2": 11,
        "-1": 10,
        "0": 9,
        "1": 8,
        "2": 7,
        "3": 6,
        "4": 5,
        "5": 4,
        "6": 3,
        "7": 2,
        "8": 1,
        "9": 0
    },
    "name": "",
    "armour": {
        "armour_id": 4,
        "armour_type": "Studded Armour",
        "ac": 6,
        "dr": 0,
        "weight_class": "Light",
        "mv": 40,
        "cost": 25,
        "weight": 20,
        "description": null
    },
    "shield": null,
    "ac": 5,
    "mv": 40,
    "weapons_melee": [
        {
            "weapon_id": 108,
            "weapon_type": "Dagger",
            "wc": 1,
            "hurlable": true,
            "hurled_rof": "3/2",
            "range_sml": "10/20/30",
            "damage": "1d4",
            "damage_2h": null,
            "cost": 4,
            "weight": 1,
            "qty": 1,
            "atk_rate": "3/2",
            "melee_atk": 1,
            "hurled_atk": 0,
            "dmg_adj": 1,
            "mastery": false
        },
        {
            "weapon_id": 137,
            "weapon_type": "Long Sword",
            "wc": 2,
            "hurlable": false,
            "hurled_rof": null,
            "range_sml": null,
            "damage": "1d8",
            "damage_2h": "1d10",
            "cost": 20,
            "weight": 4,
            "qty": 1,
            "atk_rate": "3/2",
            "melee_atk": 1,
            "hurled_atk": null,
            "dmg_adj": 1,
            "mastery": false
        }
    ],
    "weapons_missile": [
        {
            "weapon_id": 209,
            "weapon_type": "Long Bow",
            "rof": "5/2",
            "range_sml": "70/140/210",
            "damage": "1d6",
            "hurled": false,
            "launched": true,
            "cost": 60,
            "weight": 3,
            "qty": 1,
            "ammunition": "arrows \u00d712",
            "missile_atk": 1,
            "dmg_adj": 1,
            "mastery": true
        }
    ],
    "equipment": [
        "arrow quiver",
        "backpack",
        "bandages",
        "winter blanket",
        "standard rations (1 week)",
        "hemp rope (50-ft.)",
        "large sack",
        "torches \u00d73",
        "wineskin (full)"
    ],
    "money": {
        "pp": 0,
        "gp": 2,
        "ep": 0,
        "sp": 0,
        "cp": 0
    },
    "favoured_weapons": {
        "any": true,
        "weapons_melee": [
            {
                "weapon_id": 101,
                "weapon_type": "Hand Axe",
                "wc": 1,
                "hurlable": 1,
                "hurled_rof": "1/1",
                "range_sml": "15/30/45",
                "damage": "1d6",
                "damage_2h": null,
                "cost": 5,
                "weight": 2
            },
            {
                "weapon_id": 102,
                "weapon_type": "Battle Axe",
                "wc": 2,
                "hurlable": 0,
                "hurled_rof": null,
                "range_sml": null,
                "damage": "1d8",
                "damage_2h": "1d10",
                "cost": 10,
                "weight": 5
            },
            {
                "weapon_id": 103,
                "weapon_type": "Great Axe",
                "wc": 4,
                "hurlable": 0,
                "hurled_rof": null,
                "range_sml": null,
                "damage": "2d6",
                "damage_2h": null,
                "cost": 20,
                "weight": 10
            },
            {
                "weapon_id": 104,
                "weapon_type": "C\u00e6stuses",
                "wc": 0,
                "hurlable": 0,
                "hurled_rof": null,
                "range_sml": null,
                "damage": "+1",
                "damage_2h": null,
                "cost": 1,
                "weight": 1
            },
            {
                "weapon_id": 105,
                "weapon_type": "Chain Whip",
                "wc": 4,
                "hurlable": 0,
                "hurled_rof": null,
                "range_sml": null,
                "damage": "1d6",
                "damage_2h": null,
                "cost": 10,
                "weight": 3
            },
            {
                "weapon_id": 106,
                "weapon_type": "Light Club",
                "wc": 1,
                "hurlable": 1,
                "hurled_rof": "1/1",
                "range_sml": "10/20/30",
                "damage": "1d4",
                "damage_2h": null,
                "cost": 1,
                "weight": 2
            },
            {
                "weapon_id": 107,
                "weapon_type": "War Club",
                "wc": 2,
                "hurlable": 0,
                "hurled_rof": null,
                "range_sml": null,
                "damage": "1d6",
                "damage_2h": "1d8",
                "cost": 3,
                "weight": 4
            },
            {
                "weapon_id": 108,
                "weapon_type": "Dagger",
                "wc": 1,
                "hurlable": 1,
                "hurled_rof": "3/2",
                "range_sml": "10/20/30",
                "damage": "1d4",
                "damage_2h": null,
                "cost": 4,
                "weight": 1
            },
            {
                "weapon_id": 109,
                "weapon_type": "Silver Dagger",
                "wc": 1,
                "hurlable": 1,
                "hurled_rof": "3/2",
                "range_sml": "10/20/30",
                "damage": "1d4",
                "damage_2h": null,
                "cost": 25,
                "weight": 1
            },
            {
                "weapon_id": 110,
                "weapon_type": "Falcata",
                "wc": 1,
                "hurlable": 0,
                "hurled_rof": null,
                "range_sml": null,
                "damage": "1d6",
                "damage_2h": null,
                "cost": 10,
                "weight": 3
            },
            {
                "weapon_id": 111,
                "weapon_type": "Horseman's Flail",
                "wc": 1,
                "hurlable": 0,
                "hurled_rof": null,
                "range_sml": null,
                "damage": "1d6",
                "damage_2h": null,
                "cost": 5,
                "weight": 3
            },
            {
                "weapon_id": 112,
                "weapon_type": "Footman's Flail",
                "wc": 3,
                "hurlable": 0,
                "hurled_rof": null,
                "range_sml": null,
                "damage": "1d10",
                "damage_2h": null,
                "cost": 10,
                "weight": 10
            },
            {
                "weapon_id": 113,
                "weapon_type": "Halberd",
                "wc": 4,
                "hurlable": 0,
                "hurled_rof": null,
                "range_sml": null,
                "damage": "1d10",
                "damage_2h": null,
                "cost": 15,
                "weight": 8
            },
            {
                "weapon_id": 114,
                "weapon_type": "Horseman's Hammer",
                "wc": 1,
                "hurlable": 1,
                "hurled_rof": "1/1",
                "range_sml": "10/20/30",
                "damage": "1d6",
                "damage_2h": null,
                "cost": 5,
                "weight": 3
            },
            {
                "weapon_id": 115,
                "weapon_type": "War Hammer",
                "wc": 2,
                "hurlable": 0,
                "hurled_rof": null,
                "range_sml": null,
                "damage": "1d8",
                "damage_2h": "1d10",
                "cost": 10,
                "weight": 5
            },
            {
                "weapon_id": 116,
                "weapon_type": "Great Hammer",
                "wc": 4,
                "hurlable": 0,
                "hurled_rof": null,
                "range_sml": null,
                "damage": "2d6",
                "damage_2h": null,
                "cost": 20,
                "weight": 10
            },
            {
                "weapon_id": 117,
                "weapon_type": "Javelin",
                "wc": 2,
                "hurlable": 1,
                "hurled_rof": "1/1",
                "range_sml": "20/40/80",
                "damage": "1d4",
                "damage_2h": "1d6",
                "cost": 3,
                "weight": 3
            },
            {
                "weapon_id": 118,
                "weapon_type": "Lance",
                "wc": 5,
                "hurlable": 0,
                "hurled_rof": null,
                "range_sml": null,
                "damage": "1d8",
                "damage_2h": null,
                "cost": 15,
                "weight": 8
            },
            {
                "weapon_id": 119,
                "weapon_type": "Horseman's Mace",
                "wc": 1,
                "hurlable": 0,
                "hurled_rof": null,
                "range_sml": null,
                "damage": "1d6",
                "damage_2h": null,
                "cost": 4,
                "weight": 3
            },
            {
                "weapon_id": 120,
                "weapon_type": "Footman's Mace",
                "wc": 2,
                "hurlable": 0,
                "hurled_rof": null,
                "range_sml": null,
                "damage": "1d8",
                "damage_2h": "1d10",
                "cost": 10,
                "weight": 5
            },
            {
                "weapon_id": 121,
                "weapon_type": "Great Mace",
                "wc": 4,
                "hurlable": 0,
                "hurled_rof": null,
                "range_sml": null,
                "damage": "2d6",
                "damage_2h": null,
                "cost": 20,
                "weight": 10
            },
            {
                "weapon_id": 122,
                "weapon_type": "Morning Star",
                "wc": 2,
                "hurlable": 0,
                "hurled_rof": null,
                "range_sml": null,
                "damage": "1d8",
                "damage_2h": "1d10",
                "cost": 15,
                "weight": 5
            },
            {
                "weapon_id": 123,
                "weapon_type": "Horseman's Pick",
                "wc": 1,
                "hurlable": 0,
                "hurled_rof": null,
                "range_sml": null,
                "damage": "1d6",
                "damage_2h": null,
                "cost": 5,
                "weight": 3
            },
            {
                "weapon_id": 124,
                "weapon_type": "War Pick",
                "wc": 2,
                "hurlable": 0,
                "hurled_rof": null,
                "range_sml": null,
                "damage": "1d8",
                "damage_2h": "1d10",
                "cost": 15,
                "weight": 5
            },
            {
                "weapon_id": 125,
                "weapon_type": "Pike",
                "wc": 6,
                "hurlable": 0,
                "hurled_rof": null,
                "range_sml": null,
                "damage": "1d8",
                "damage_2h": null,
                "cost": 7,
                "weight": 12
            },
            {
                "weapon_id": 126,
                "weapon_type": "Quarterstaff",
                "wc": 3,
                "hurlable": 0,
                "hurled_rof": null,
                "range_sml": null,
                "damage": "1d6",
                "damage_2h": null,
                "cost": 5,
                "weight": 5
            },
            {
                "weapon_id": 127,
                "weapon_type": "Short Scimitar",
                "wc": 1,
                "hurlable": 0,
                "hurled_rof": null,
                "range_sml": null,
                "damage": "1d6",
                "damage_2h": null,
                "cost": 10,
                "weight": 3
            },
            {
                "weapon_id": 128,
                "weapon_type": "Long Scimitar",
                "wc": 2,
                "hurlable": 0,
                "hurled_rof": null,
                "range_sml": null,
                "damage": "1d8",
                "damage_2h": "1d10",
                "cost": 20,
                "weight": 4
            },
            {
                "weapon_id": 129,
                "weapon_type": "Two-Handed Scimitar",
                "wc": 4,
                "hurlable": 0,
                "hurled_rof": null,
                "range_sml": null,
                "damage": "3d4",
                "damage_2h": null,
                "cost": 40,
                "weight": 6
            },
            {
                "weapon_id": 130,
                "weapon_type": "Sickle",
                "wc": 1,
                "hurlable": 0,
                "hurled_rof": null,
                "range_sml": null,
                "damage": "1d4",
                "damage_2h": null,
                "cost": 3,
                "weight": 2
            },
            {
                "weapon_id": 131,
                "weapon_type": "Short Spear",
                "wc": 3,
                "hurlable": 1,
                "hurled_rof": "1/1",
                "range_sml": "15/30/45",
                "damage": "1d6",
                "damage_2h": "1d8",
                "cost": 4,
                "weight": 5
            },
            {
                "weapon_id": 132,
                "weapon_type": "Long Spear",
                "wc": 4,
                "hurlable": 0,
                "hurled_rof": null,
                "range_sml": null,
                "damage": "1d6",
                "damage_2h": "1d8",
                "cost": 5,
                "weight": 7
            },
            {
                "weapon_id": 133,
                "weapon_type": "Great Spear",
                "wc": 5,
                "hurlable": 0,
                "hurled_rof": null,
                "range_sml": null,
                "damage": "1d8",
                "damage_2h": null,
                "cost": 7,
                "weight": 9
            },
            {
                "weapon_id": 134,
                "weapon_type": "Spiked Staff",
                "wc": 3,
                "hurlable": 0,
                "hurled_rof": null,
                "range_sml": null,
                "damage": "1d10",
                "damage_2h": null,
                "cost": 15,
                "weight": 7
            },
            {
                "weapon_id": 135,
                "weapon_type": "Short Sword",
                "wc": 1,
                "hurlable": 0,
                "hurled_rof": null,
                "range_sml": null,
                "damage": "1d6",
                "damage_2h": null,
                "cost": 10,
                "weight": 3
            },
            {
                "weapon_id": 136,
                "weapon_type": "Broad Sword",
                "wc": 2,
                "hurlable": 0,
                "hurled_rof": null,
                "range_sml": null,
                "damage": "1d8",
                "damage_2h": "1d10",
                "cost": 20,
                "weight": 4
            },
            {
                "weapon_id": 137,
                "weapon_type": "Long Sword",
                "wc": 2,
                "hurlable": 0,
                "hurled_rof": null,
                "range_sml": null,
                "damage": "1d8",
                "damage_2h": "1d10",
                "cost": 20,
                "weight": 4
            },
            {
                "weapon_id": 138,
                "weapon_type": "Bastard Sword",
                "wc": 3,
                "hurlable": 0,
                "hurled_rof": null,
                "range_sml": null,
                "damage": "1d8",
                "damage_2h": "2d6",
                "cost": 30,
                "weight": 5
            },
            {
                "weapon_id": 139,
                "weapon_type": "Two-Handed Sword",
                "wc": 4,
                "hurlable": 0,
                "hurled_rof": null,
                "range_sml": null,
                "damage": "3d4",
                "damage_2h": null,
                "cost": 40,
                "weight": 6
            },
            {
                "weapon_id": 140,
                "weapon_type": "Tonfa",
                "wc": 1,
                "hurlable": 0,
                "hurled_rof": null,
                "range_sml": null,
                "damage": "1d4",
                "damage_2h": null,
                "cost": 2,
                "weight": 1
            },
            {
                "weapon_id": 141,
                "weapon_type": "Hand Trident",
                "wc": 1,
                "hurlable": 0,
                "hurled_rof": null,
                "range_sml": null,
                "damage": "1d4",
                "damage_2h": null,
                "cost": 7,
                "weight": 1
            },
            {
                "weapon_id": 142,
                "weapon_type": "Long Trident",
                "wc": 4,
                "hurlable": 1,
                "hurled_rof": "1/1",
                "range_sml": "10/20/30",
                "damage": "1d6",
                "damage_2h": "1d8",
                "cost": 10,
                "weight": 6
            },
            {
                "weapon_id": 143,
                "weapon_type": "Whip",
                "wc": 5,
                "hurlable": 0,
                "hurled_rof": null,
                "range_sml": null,
                "damage": "1d2",
                "damage_2h": null,
                "cost": 1,
                "weight": 2
            }
        ],
        "weapons_missile": [
            {
                "weapon_id": 201,
                "weapon_type": "Bola",
                "rof": "1/1",
                "range_sml": "15/30/45",
                "damage": "1d2",
                "hurled": 1,
                "launched": 0,
                "cost": 3,
                "weight": 2
            },
            {
                "weapon_id": 202,
                "weapon_type": "Boomerang",
                "rof": "1/1",
                "range_sml": "50/100/150",
                "damage": "1d4",
                "hurled": 1,
                "launched": 0,
                "cost": 1,
                "weight": 1
            },
            {
                "weapon_id": 203,
                "weapon_type": "Dart",
                "rof": "2/1",
                "range_sml": "15/30/45",
                "damage": "1d3",
                "hurled": 1,
                "launched": 0,
                "cost": 1,
                "weight": 1
            },
            {
                "weapon_id": 204,
                "weapon_type": "Hooked Throwing Knife",
                "rof": "1/1",
                "range_sml": "30/60/90",
                "damage": "1d6",
                "hurled": 1,
                "launched": 0,
                "cost": 20,
                "weight": 2
            },
            {
                "weapon_id": 205,
                "weapon_type": "Lasso",
                "rof": "1/2",
                "range_sml": "20 feet",
                "damage": null,
                "hurled": 1,
                "launched": 0,
                "cost": 3,
                "weight": 3
            },
            {
                "weapon_id": 206,
                "weapon_type": "Fighting Net",
                "rof": "1/2",
                "range_sml": "10 feet",
                "damage": null,
                "hurled": 1,
                "launched": 0,
                "cost": 5,
                "weight": 7
            },
            {
                "weapon_id": 207,
                "weapon_type": "Stone",
                "rof": "2/1",
                "range_sml": "30/60/90",
                "damage": "1",
                "hurled": 1,
                "launched": 0,
                "cost": null,
                "weight": 1
            },
            {
                "weapon_id": 208,
                "weapon_type": "Blowgun",
                "rof": "1/1",
                "range_sml": "30/60/90",
                "damage": "1",
                "hurled": 0,
                "launched": 1,
                "cost": 5,
                "weight": 1
            },
            {
                "weapon_id": 209,
                "weapon_type": "Long Bow",
                "rof": "3/2",
                "range_sml": "70/140/210",
                "damage": "1d6",
                "hurled": 0,
                "launched": 1,
                "cost": 60,
                "weight": 3
            },
            {
                "weapon_id": 210,
                "weapon_type": "Composite Long Bow",
                "rof": "3/2",
                "range_sml": "80/160/240",
                "damage": "1d6",
                "hurled": 0,
                "launched": 1,
                "cost": 100,
                "weight": 3
            },
            {
                "weapon_id": 211,
                "weapon_type": "Short Bow",
                "rof": "3/2",
                "range_sml": "50/100/150",
                "damage": "1d6",
                "hurled": 0,
                "launched": 1,
                "cost": 20,
                "weight": 2
            },
            {
                "weapon_id": 212,
                "weapon_type": "Composite Short Bow",
                "rof": "3/2",
                "range_sml": "60/120/180",
                "damage": "1d6",
                "hurled": 0,
                "launched": 1,
                "cost": 50,
                "weight": 2
            },
            {
                "weapon_id": 213,
                "weapon_type": "Heavy Crossbow",
                "rof": "1/2",
                "range_sml": "80/160/240",
                "damage": "1d6+2",
                "hurled": 0,
                "launched": 1,
                "cost": 25,
                "weight": 10
            },
            {
                "weapon_id": 214,
                "weapon_type": "Light Crossbow",
                "rof": "1/1",
                "range_sml": "60/120/180",
                "damage": "1d6+1",
                "hurled": 0,
                "launched": 1,
                "cost": 15,
                "weight": 5
            },
            {
                "weapon_id": 215,
                "weapon_type": "Repeating Crossbow",
                "rof": "3/1",
                "range_sml": "50/100/150",
                "damage": "1d6",
                "hurled": 0,
                "launched": 1,
                "cost": 100,
                "weight": 6
            },
            {
                "weapon_id": 216,
                "weapon_type": "Sling",
                "rof": "1/1",
                "range_sml": "50/100/150",
                "damage": "1d4",
                "hurled": 0,
                "launched": 1,
                "cost": 2,
                "weight": 1
            }
        ],
        "unskilled_penalty": 0
    },
    "thief_skills": [
        {
            "thief_skill": "climb",
            "skill_name": "Climb",
            "skill_roll": 10,
            "stat": "dx"
        },
        {
            "thief_skill": "discern_noise",
            "skill_name": "Discern Noise",
            "skill_roll": 9,
            "stat": "ws"
        },
        {
            "thief_skill": "hide",
            "skill_name": "Hide",
            "skill_roll": 10,
            "stat": "dx"
        },
        {
            "thief_skill": "move_silently",
            "skill_name": "Move Silently",
            "skill_roll": 10,
            "stat": "dx"
        }
    ],
    "turn_undead_matrix": null,
    "spells": {
        "drd": {
            "spells_per_day": {
                "lvl1": 1,
                "lvl2": 1,
                "lvl3": 1,
                "lvl4": 0,
                "lvl5": 0,
                "lvl6": 0
            },
            "spells_known": [
                {
                    "school": "drd",
                    "spell_level": 1,
                    "spell_id": 370,
                    "spell_name": "Speak with Animals",
                    "range": "20 feet",
                    "duration": "1 turn",
                    "reversible": false,
                    "pp": 232,
                    "spell_desc": "<p>Allows the sorcerer to communicate with any normal sort of animal (not magical beasts, monsters, or other supernatural creatures). The animals will reply in kind; such responses are usually limited to brief one- or twoword statements predicated on the intelligence of the animal, at the referee\u2019s discretion. Friendly animals might be convinced to perform some minor service.</p>"
                },
                {
                    "school": "drd",
                    "spell_level": 2,
                    "spell_id": 25,
                    "spell_name": "Barkskin",
                    "range": "touch",
                    "duration": "1 turn + 1 turn per CA level",
                    "reversible": false,
                    "pp": 178,
                    "spell_desc": "<p>Toughens the recipient\u2019s flesh to the strength of oak bark, providing an armour class equivalent to chain mail (AC 5, DR 1), or +1 AC if other armour is worn. <i>Barkskin</i> does not encumber the recipient in any way.</p>"
                },
                {
                    "school": "drd",
                    "spell_level": 3,
                    "spell_id": 27,
                    "spell_name": "Black Cloud",
                    "range": null,
                    "duration": null,
                    "reversible": null,
                    "pp": null,
                    "spell_desc": null
                }
            ]
        },
        "mag": {
            "spells_per_day": {
                "lvl1": 2,
                "lvl2": 1,
                "lvl3": 0,
                "lvl4": 0,
                "lvl5": 0,
                "lvl6": 0
            },
            "spells_known": [
                {
                    "school": "mag",
                    "spell_level": 1,
                    "spell_id": 258,
                    "spell_name": "Message",
                    "range": "1 mile",
                    "duration": "1 round per CA level",
                    "reversible": false,
                    "pp": 214,
                    "spell_desc": "<p>The sorcerer points at the recipient and whispers a <i>message</i> that is heard as though the two stood side by side. The recipient can then reply if the spell\u2019s duration has not elapsed. The caster and the recipient must be able to see each other. If the spell is cast at an unwilling target, a <i>sorcery</i> saving throw can be made to block the audibility of the spell.</p>"
                },
                {
                    "school": "mag",
                    "spell_level": 2,
                    "spell_id": 143,
                    "spell_name": "Extrasensory Perception",
                    "range": "60 feet",
                    "duration": "1 round per CA level",
                    "reversible": false,
                    "pp": 196,
                    "spell_desc": "<p>Allows the caster, who must pinch a copper coin betwixt thumb and forefinger, to detect the vague surface thoughts (not precise words) of any creature within the spell\u2019s range, so long as the creature has thoughts. (Most undead and constructs, for example, do not.) <i>Extrasensory perception</i> targets a single creature; once selected, another cannot be targeted. No saving throw is allowed unless the target is of 6 HD or greater. If so, a <i>sorcery</i> saving throw, modified by <i>willpower adjustment</i>, if applicable, must be made. When reading the surface thoughts of a lower-order creature, only its most basic instincts will be revealed. The spell also can be used to determine if a monster lurks behind a door or down a dark tunnel (so long as the monster is within range). The spell can penetrate one inch of metal, six inches of stone, or one foot of wood; however, the thinnest sheet of lead will obstruct it.</p>"
                }
            ]
        }
    },
    "class_abilities": [
        {
            "class_id": 10,
            "level": 1,
            "ability_title": "Alertness",
            "brief_desc": "-1 chance to be surprized",
            "ability_desc": null
        },
        {
            "class_id": 10,
            "level": 1,
            "ability_title": "Ambusher",
            "brief_desc": "+1 chance to surprize others",
            "ability_desc": null
        },
        {
            "class_id": 10,
            "level": 1,
            "ability_title": "Extraordinary",
            "brief_desc": "+8% feat of ST",
            "ability_desc": null
        },
        {
            "class_id": 10,
            "level": 1,
            "ability_title": "Otherworldly Enemies",
            "brief_desc": "+1 dmg per level vs. otherworldly creatures",
            "ability_desc": null
        },
        {
            "class_id": 10,
            "level": 1,
            "ability_title": "Track",
            "brief_desc": "10:12 in wilderness, else 3:12",
            "ability_desc": null
        },
        {
            "class_id": 10,
            "level": 1,
            "ability_title": "Track Concealment",
            "brief_desc": "obscure tracks of # of companions equal to level, half speed",
            "ability_desc": null
        },
        {
            "class_id": 10,
            "level": 1,
            "ability_title": "Traverse Overgrowth",
            "brief_desc": "negotiate difficult wilderness at full speed without leaving tracks",
            "ability_desc": null
        },
        {
            "class_id": 10,
            "level": 1,
            "ability_title": "Weapon Mastery",
            "brief_desc": "+1 atk/dmg, increased attack rate with one weapon",
            "ability_desc": null
        },
        {
            "class_id": 10,
            "level": 1,
            "ability_title": "Wilderness Survival",
            "brief_desc": null,
            "ability_desc": null
        },
        {
            "class_id": 10,
            "level": 4,
            "ability_title": "Weapon Mastery",
            "brief_desc": "additional weapon mastery",
            "ability_desc": null
        },
        {
            "class_id": 10,
            "level": 6,
            "ability_title": "Enlist Henchmen",
            "brief_desc": null,
            "ability_desc": null
        },
        {
            "class_id": 10,
            "level": 7,
            "ability_title": "Melee Expert",
            "brief_desc": "improved melee attack rate",
            "ability_desc": null
        },
        {
            "class_id": 10,
            "level": 7,
            "ability_title": "Scroll Use",
            "brief_desc": "druid scrolls at 7th level; magician scrolls at 8th level",
            "ability_desc": null
        },
        {
            "class_id": 10,
            "level": 7,
            "ability_title": "Sorcery",
            "brief_desc": "druid spells at 7th level; magician spells at 8th level",
            "ability_desc": null
        },
        {
            "class_id": 10,
            "level": 8,
            "ability_title": "Weapon Mastery",
            "brief_desc": "additional weapon mastery",
            "ability_desc": null
        },
        {
            "class_id": 10,
            "level": 9,
            "ability_title": "Lordship",
            "brief_desc": null,
            "ability_desc": null
        }
    ]
}
