{
    "method": 6,
    "class_id": 26,
    "class_name": "Scout",
    "attr": {
        "st": {
            "score": 9,
            "atk_mod": 0,
            "dmg_adj": 0,
            "test": 2,
            "feat": 4
        },
        "dx": {
            "score": 11,
            "atk_mod": 0,
            "def_adj": 0,
            "test": 2,
            "feat": 12
        },
        "cn": {
            "score": 15,
            "hp_adj": 1,
            "poison_adj": 1,
            "trauma_surv": 85,
            "test": 3,
            "feat": 16
        },
        "in": {
            "score": 12,
            "lang": 0,
            "bonus_spells": 0,
            "learn_spell": 50
        },
        "ws": {
            "score": 13,
            "will_adj": 0,
            "bonus_spells": 1,
            "learn_spell": 65
        },
        "ch": {
            "score": 8,
            "react_adj": -1,
            "max_henchmen": 3,
            "turn_adj": 0
        }
    },
    "xp": 560000,
    "level": 12,
    "xp_to_next": null,
    "xp_bonus": false,
    "alignment": {
        "align_id": 5,
        "short_name": "N",
        "long_name": "Neutral"
    },
    "deity": {
        "deity_id": 14,
        "deity_name": "Rel",
        "primary_alignment": "Neutral"
    },
    "race_id": 1,
    "race": "Common",
    "gender": "Male",
    "hd": "9d6+6",
    "hp": 53,
    "fa": 8,
    "ca": 0,
    "ta": 0,
    "sv": 11,
    "sv_bonus": {
        "death": 0,
        "transformation": 0,
        "device": 2,
        "avoidance": 2,
        "sorcery": 0
    },
    "combat_matrix": {
        "-9": 21,
        "-8": 20,
        "-7": 19,
        "-6": 18,
        "-5": 17,
        "-4": 16,
        "-3": 15,
        "-2": 14,
        "-1": 13,
        "0": 12,
        "1": 11,
        "2": 10,
        "3": 9,
        "4": 8,
        "5": 7,
        "6": 6,
        "7": 5,
        "8": 4,
        "9": 3
    },
    "name": "",
    "armour": {
        "armour_id": 2,
        "armour_type": "Padded Armour",
        "ac": 8,
        "dr": 0,
        "weight_class": "Light",
        "mv": 40,
        "cost": 10,
        "weight": 10,
        "description": null
    },
    "shield": {
        "shield_id": 1,
        "shield_type": "Small Shield",
        "def_mod": 1,
        "cost": 5,
        "weight": 5
    },
    "ac": 7,
    "mv": 50,
    "weapons_melee": [
        {
            "weapon_id": 101,
            "weapon_type": "Hand Axe",
            "wc": 1,
            "hurlable": true,
            "hurled_rof": "1/1",
            "range_sml": "15/30/45",
            "damage": "1d6",
            "damage_2h": null,
            "cost": 5,
            "weight": 2,
            "qty": 2,
            "atk_rate": "1/1",
            "melee_atk": 0,
            "hurled_atk": 0,
            "dmg_adj": 0,
            "mastery": false
        }
    ],
    "weapons_missile": [
        {
            "weapon_id": 203,
            "weapon_type": "Dart",
            "rof": "2/1",
            "range_sml": "15/30/45",
            "damage": "1d3",
            "hurled": true,
            "launched": false,
            "cost": 1,
            "weight": 1,
            "qty": 4,
            "ammunition": null,
            "missile_atk": 0,
            "dmg_adj": 0,
            "mastery": false
        }
    ],
    "equipment": [
        "backpack",
        "bandages",
        "winter blanket",
        "chalk (piece)",
        "disguise clothing",
        "grappling hook",
        "grease",
        "marbles \u00d720",
        "parchment",
        "wooden pole (10-ft.)",
        "soft leather pouch",
        "iron rations (1 week)",
        "hemp rope (50-ft.)",
        "small sack",
        "thieves\u2019 tools",
        "tinderbox",
        "torches \u00d73",
        "wineskin (full)",
        "writing stick"
    ],
    "money": {
        "pp": 0,
        "gp": 5,
        "ep": 0,
        "sp": 0,
        "cp": 0
    },
    "thief_skills": [
        {
            "thief_skill": "climb",
            "skill_name": "Climb",
            "skill_roll": 10,
            "stat": "dx"
        },
        {
            "thief_skill": "discern_noise",
            "skill_name": "Discern Noise",
            "skill_roll": 9,
            "stat": "ws"
        },
        {
            "thief_skill": "hide",
            "skill_name": "Hide",
            "skill_roll": 10,
            "stat": "dx"
        },
        {
            "thief_skill": "manipulate_traps",
            "skill_name": "Manipulate Traps",
            "skill_roll": 8,
            "stat": "dx"
        },
        {
            "thief_skill": "move_silently",
            "skill_name": "Move Silently",
            "skill_roll": 10,
            "stat": "dx"
        },
        {
            "thief_skill": "open_locks",
            "skill_name": "Open Locks",
            "skill_roll": 8,
            "stat": "dx"
        }
    ],
    "turn_undead_matrix": null,
    "spells": null,
    "class_abilities": [
        {
            "class_id": 26,
            "level": 1,
            "ability_title": "Agile",
            "brief_desc": "+1 AC when unarmoured",
            "ability_desc": null
        },
        {
            "class_id": 26,
            "level": 1,
            "ability_title": "Alertness",
            "brief_desc": "-1 chance to be surprized",
            "ability_desc": null
        },
        {
            "class_id": 26,
            "level": 1,
            "ability_title": "Backstab",
            "brief_desc": "+4 to hit, damage multiplied",
            "ability_desc": null
        },
        {
            "class_id": 26,
            "level": 1,
            "ability_title": "Controlled Fall",
            "brief_desc": "ignore 10' per level of falling damage (if near stable surface)",
            "ability_desc": null
        },
        {
            "class_id": 26,
            "level": 1,
            "ability_title": "Detect Secret Doors",
            "brief_desc": "3:6 chance",
            "ability_desc": null
        },
        {
            "class_id": 26,
            "level": 1,
            "ability_title": "Determine Depth and Grade",
            "brief_desc": "chance to determine depth of pit or slope of passages",
            "ability_desc": null
        },
        {
            "class_id": 26,
            "level": 1,
            "ability_title": "Disguise",
            "brief_desc": "alter appearance as per disguise self spell",
            "ability_desc": null
        },
        {
            "class_id": 26,
            "level": 1,
            "ability_title": "Extraordinary",
            "brief_desc": "+8% feat of DX",
            "ability_desc": null
        },
        {
            "class_id": 26,
            "level": 1,
            "ability_title": "Run",
            "brief_desc": "MV 50' if light or no armour",
            "ability_desc": null
        },
        {
            "class_id": 26,
            "level": 1,
            "ability_title": "Track",
            "brief_desc": "7:12 in wilderness, else 9:12",
            "ability_desc": null
        },
        {
            "class_id": 26,
            "level": 4,
            "ability_title": "New Weapon Skill",
            "brief_desc": null,
            "ability_desc": null
        },
        {
            "class_id": 26,
            "level": 6,
            "ability_title": "Enlist Henchmen",
            "brief_desc": null,
            "ability_desc": null
        },
        {
            "class_id": 26,
            "level": 8,
            "ability_title": "New Weapon Skill",
            "brief_desc": null,
            "ability_desc": null
        },
        {
            "class_id": 26,
            "level": 9,
            "ability_title": "Lordship",
            "brief_desc": null,
            "ability_desc": null
        },
        {
            "class_id": 26,
            "level": 12,
            "ability_title": "New Weapon Skill",
            "brief_desc": null,
            "ability_desc": null
        }
    ]
}